{
    "pools": [
        {
            "name": "horror",
            "rolls": 1,
            "entries": [
                {
                    "type": "item",
                    "weight": 1,
                    "name": "mm:azure_maelstrom_core_crystal",
                    "conditions": [
                        {
                            "condition": "random_chance_with_looting",
                            "chance": 0.04,
                            "looting_multiplier": 0.01
                        }
                    ]
                }
            ]
        },
        {
            "name": "horror",
            "rolls": 1,
            "entries": [
                {
                    "type": "item",
                    "weight": 1,
                    "name": "mm:maelstrom_cannon",
                    "conditions": [
                        {
                            "condition": "random_chance_with_looting",
                            "chance": 0.05,
                            "looting_multiplier": 0.01
                        }
                    ]
                }
            ]
        }
    ]
}
